[
  {
    "id": "1",
    "image_url": "/images/cat.jpeg",
    "name": "고양이",
    "age": "4살",
    "gender": "male",
    "address": "춘천"
  },
  {
    "id": "2",
    "image_url": "/images/cat.jpeg",
    "name": "고냥이",
    "age": "14살",
    "gender": "female",
    "address": "양평"
  },
  {
    "id": "3",
    "image_url": "/images/cat.jpeg",
    "name": "고용이",
    "age": "7살",
    "gender": "male",
    "address": "천안"
  },
  {
    "id": "4",
    "image_url": "/images/cat.jpeg",
    "name": "모울이",
    "age": "1살",
    "gender": "felmale",
    "address": "부산"
  },
  {
    "id": "5",
    "image_url": "/images/cat.jpeg",
    "name": "곰율이",
    "age": "3살",
    "gender": "male",
    "address": "노원"
  },
  {
    "id": "6",
    "image_url": "/images/cat.jpeg",
    "name": "고울이",
    "age": "11살",
    "gender": "male",
    "address": "평양"
  },
  {
    "id": "7",
    "image_url": "/images/cat.jpeg",
    "name": "고물이",
    "age": "9살",
    "gender": "male",
    "address": "진주"
  },
  {
    "id": "8",
    "image_url": "/images/cat.jpeg",
    "name": "기양이",
    "age": "2살",
    "gender": "male",
    "address": "충청"
  }
]
